LICENSE
upload_to/__init__.py
upload_to/validators.py
django_upload_to-1.0.0.dist-info/LICENSE
django_upload_to-1.0.0.dist-info/METADATA
django_upload_to-1.0.0.dist-info/WHEEL
django_upload_to-1.0.0.dist-info/RECORD
