Metadata-Version: 2.1
Name: django-upload-to
Version: 1.0.0
Summary: It generates dynamically a directory path and a file name for Django FileField
Home-page: https://github.com/valbertovc/django-upload-to
Keywords: django,file,media,upload
Author: Valberto Carneiro
Author-email: valbertovc@gmail.com
Requires-Python: >=3.8,<4
Classifier: Development Status :: 4 - Beta
Classifier: Framework :: Django :: 2
Classifier: Framework :: Django :: 2.2
Classifier: Framework :: Django :: 3
Classifier: Framework :: Django :: 3.2
Classifier: Framework :: Django :: 4
Classifier: Framework :: Django :: 4.1
Classifier: Framework :: Django :: 5.0
Classifier: Intended Audience :: Developers
Classifier: License :: OSI Approved :: MIT License
Classifier: Operating System :: OS Independent
Classifier: Programming Language :: Python
Classifier: Programming Language :: Python :: 3
Classifier: Programming Language :: Python :: 3.8
Classifier: Programming Language :: Python :: 3.9
Classifier: Programming Language :: Python :: 3.10
Classifier: Programming Language :: Python :: 3.11
Classifier: Programming Language :: Python :: 3.12
Classifier: Topic :: Multimedia
Classifier: Topic :: Software Development :: Libraries :: Application Frameworks
Requires-Dist: Django (>=4.0.0)
Project-URL: Bug Tracker, https://github.com/valbertovc/django-upload-to/issues
Project-URL: Changelog, https://github.com/valbertovc/django-upload-to/releases
Project-URL: Homepage, https://valbertovc.github.io/django-upload-to/
Project-URL: Repository, https://github.com/valbertovc/django-upload-to
